{
  "entries": [
    {
      "url": "https://www.auto.cz/zapomente-na-apple-nebo-sony-na-vlastni-auto-laka-sit-cerpacich-stanic-shell-160796",
      "title": "Benzín v ČR: 42,30 Kč/l – co to znamená pro řidiče",
      "simhash": 6811436043039591586,
      "ngrams_hash": "e4d8f691c4185621",
      "entities": [
        "jako",
        "nadace",
        "nafta",
        "kolik",
        "mpo",
        "podle",
        "shellu",
        "shell",
        "usd",
        "kde",
        "ale",
        "čnb",
        "prahou",
        "natural",
        "kurzy",
        "zdroj",
        "česmad",
        "omv",
        "opec",
        "lpg",
        "brna",
        "praze",
        "natural 95",
        "jak",
        "rusko",
        "pro",
        "litr",
        "mol",
        "brent"
      ],
      "created_at": "2026-04-28T17:18:46.087784+02:00"
    },
    {
      "url": "https://www.e15.cz/investice/investicni-online-ropa-kvuli-konfliktu-na-blizkem-vychode-dal-zdrazuje-1424330",
      "title": "Benzín a nafta: Ceny v ČR se zvyšují",
      "simhash": 6090292462367726754,
      "ngrams_hash": "89879b1c06825a50",
      "entities": [
        "jako",
        "nafta",
        "kolik",
        "jana",
        "shell",
        "usd",
        "kde",
        "pergol",
        "čnb",
        "natural",
        "zdroj",
        "pokud",
        "česmad",
        "ceny",
        "omv",
        "opec",
        "lpg",
        "orlen",
        "brna",
        "praze",
        "natural 95",
        "jak",
        "pro",
        "mol",
        "tip",
        "ropa brent",
        "litr natural",
        "kurz",
        "brent"
      ],
      "created_at": "2026-04-28T17:17:02.588095+02:00"
    },
    {
      "url": "https://zpravy.aktualne.cz/ekonomika/auto/technika-a-design/evropa-resi-penalty-cina-vyrabi-auta-sefdesigner-jozef-kaban-popisuje-stret-dvou-svetu/r~aaa294deb0b5e38bedff2efbd127fb0a/",
      "title": "Benzín v ČR: 42,30 Kč/l – co to znamená pro řidiče",
      "simhash": 16055122279040408578,
      "ngrams_hash": "b609aa88fbde8b23",
      "entities": [
        "natural 95",
        "prahy",
        "kolik",
        "lpg",
        "pro",
        "kde",
        "natural",
        "jak",
        "jan",
        "nafta",
        "nadace",
        "brent",
        "zdroj",
        "brna",
        "čnb",
        "most",
        "pergol",
        "opec",
        "praze",
        "pokud",
        "jih",
        "ostrava"
      ],
      "created_at": "2026-04-28T09:37:43.286897+02:00"
    },
    {
      "url": "https://www.novinky.cz/clanek/auto-stellantis-se-v-krizi-zacne-soustredit-na-ctyri-klicove-znacky-dalsich-deset-automobilek-se-prizpusobi-40575551",
      "title": "Benzín v ČR: ceny, tankování a co čekat v roce 2026",
      "simhash": 6092530948082687154,
      "ngrams_hash": "dc0fdb043c498e3d",
      "entities": [
        "natural 95",
        "prahy",
        "kurz",
        "kolik",
        "litr",
        "lpg",
        "pro",
        "kde",
        "natural",
        "jak",
        "jan",
        "nafta",
        "omv",
        "nadace",
        "jako",
        "brent",
        "zdroj",
        "brna",
        "čnb",
        "mpo",
        "opec",
        "praze",
        "shell",
        "jeho",
        "pokud",
        "česmad",
        "usd"
      ],
      "created_at": "2026-04-28T09:35:01.824465+02:00"
    },
    {
      "url": "https://www.e15.cz/byznys/prumysl-a-energetika/regulace-cen-benzinu-a-nafty-bude-pokracovat-i-v-kvetnu-oznamila-schillerova-1432421",
      "title": "Benzín a nafta: 400 Kč úspora na plné nádrži v květnu",
      "simhash": 2075883030314704050,
      "ngrams_hash": "90421b15b96f2a96",
      "entities": [
        "aleny",
        "dnes",
        "natural 95",
        "tato",
        "podle",
        "kolik",
        "lpg",
        "pro",
        "kde",
        "natural",
        "jak",
        "jan",
        "nafta",
        "omv",
        "combie",
        "jako",
        "brent",
        "zdroj",
        "čnb",
        "mol",
        "orlen",
        "mpo",
        "ostravy",
        "opec",
        "praze",
        "shell",
        "pokud",
        "česmad"
      ],
      "created_at": "2026-04-28T09:33:01.862217+02:00"
    },
    {
      "url": "https://ct24.ceskatelevize.cz/clanek/svet/hodnota-majetku-ruskych-miliardaru-i-pres-sankce-rekordne-vzrostla-pise-forbes-372710",
      "title": "Benzín a nafta v ČR: ceny, tankování a výhled na 2026",
      "simhash": 6666740020758170802,
      "ngrams_hash": "17448bd29b94487c",
      "entities": [
        "ceny",
        "pokud",
        "kde",
        "tip",
        "usd",
        "brent",
        "opec",
        "natural 95",
        "kolik",
        "zdroj",
        "pro",
        "mol",
        "tyto",
        "lpg",
        "jako",
        "jak",
        "rusku",
        "orlen",
        "nafta",
        "shell",
        "čnb",
        "ostravy",
        "praze",
        "omv",
        "natural"
      ],
      "created_at": "2026-04-27T17:00:37.900149+02:00"
    },
    {
      "url": "https://www.novinky.cz/clanek/auto-foto-automobilove-klenoty-se-ukazaly-na-golfovem-hristi-v-praze-40575361",
      "title": "Benzín a nafta v ČR: 42,30 Kč/l – co to znamená pro řidiče",
      "simhash": 6810309868254846114,
      "ngrams_hash": "bb4442e82ae09bf7",
      "entities": [
        "pokud",
        "brna",
        "eu",
        "kde",
        "tip",
        "usd",
        "brent",
        "opec",
        "nadace",
        "natural 95",
        "litr",
        "kolik",
        "zdroj",
        "pro",
        "mpo",
        "mol",
        "club",
        "lpg",
        "jako",
        "jak",
        "nafta",
        "shell",
        "čnb",
        "praze",
        "česmad",
        "omv",
        "natural"
      ],
      "created_at": "2026-04-27T16:58:58.547152+02:00"
    },
    {
      "url": "https://www.e15.cz/investice/investicni-online-regulace-cen-benzinu-a-nafty-bude-pokracovat-chybi-ale-podpis-zakona-1424330",
      "title": "Benzín a nafta v ČR: ceny se zvyšují, co to znamená pro řid…",
      "simhash": 6666755705978670258,
      "ngrams_hash": "bb823c0182a9d049",
      "entities": [
        "ceny",
        "litr natural",
        "kurz",
        "pokud",
        "brna",
        "kde",
        "usd",
        "brent",
        "opec",
        "natural 95",
        "kolik",
        "prahy",
        "zdroj",
        "pro",
        "mpo",
        "regulace",
        "mol",
        "tyto",
        "kurzy",
        "lpg",
        "pergol",
        "jak",
        "orlen",
        "nafta",
        "ministerstvo",
        "shell",
        "combie",
        "čnb",
        "praze",
        "česmad",
        "omv",
        "natural"
      ],
      "created_at": "2026-04-27T16:57:23.541280+02:00"
    },
    {
      "url": "https://zpravy.aktualne.cz/ekonomika/jarni-potravinove-sbirky-se-zucastnil-rekordni-pocet-obchodu-vybralo-se-o-sto-tun-vic-nez-loni/r~aaa295e124d0f7e5673074d9bae58881/",
      "title": "Benzín v ČR: ceny, tankování a tipy na nejlevnější čerpací…",
      "simhash": 6632694759929056434,
      "ngrams_hash": "336f1bbb0e5a81e0",
      "entities": [
        "podle",
        "praze",
        "mol",
        "jak",
        "omv",
        "čnb",
        "shell",
        "kde",
        "orlen",
        "pro",
        "česmad",
        "pokud",
        "usd",
        "brent",
        "tyto",
        "kurz",
        "nafta",
        "mpo",
        "brna",
        "kolik",
        "zdroj",
        "litr",
        "natural 95",
        "opec",
        "natural",
        "combie",
        "lpg"
      ],
      "created_at": "2026-04-27T10:45:57.964033+02:00"
    },
    {
      "url": "https://www.e15.cz/byznys/technologie-a-media/propast-se-prohlubuje-ai-rusi-tisice-mist-v-it-nova-vznikaji-jen-pro-vyvolene-1432395",
      "title": "Benzín a nafta: Ceny se zvedají, co to znamená pro řidiče",
      "simhash": 6810307944168283314,
      "ngrams_hash": "bda75ce1caf067fe",
      "entities": [
        "podle",
        "praze",
        "mol",
        "jak",
        "čnb",
        "shell",
        "konkurence",
        "kde",
        "orlen",
        "pro",
        "česmad",
        "pokud",
        "usd",
        "jan",
        "brent",
        "indie",
        "nafta",
        "kolik",
        "zdroj",
        "ceny",
        "natural 95",
        "opec",
        "natural",
        "ropa brent",
        "zde",
        "lpg",
        "rusku"
      ],
      "created_at": "2026-04-27T10:44:09.389538+02:00"
    },
    {
      "url": "https://ct24.ceskatelevize.cz/clanek/domaci/maximalni-ceny-paliv-o-vikendu-opet-o-vyssi-desitky-haleru-vzrostou-372764",
      "title": "Benzín a nafta: ceny vzrostou o desítky haléřů o víkendu",
      "simhash": 15852693752480717986,
      "ngrams_hash": "3a403e381726b892",
      "entities": [
        "praze",
        "mol",
        "omv",
        "čnb",
        "jako",
        "kde",
        "pro",
        "pokud",
        "brent",
        "tyto",
        "nafta",
        "brna",
        "kolik",
        "zdroj",
        "natural 95",
        "opec",
        "natural",
        "combie",
        "prahy",
        "lpg",
        "ostravy",
        "ministerstvo"
      ],
      "created_at": "2026-04-27T10:42:17.776711+02:00"
    }
  ]
}