{
  "last_run_ts": 1777534046,
  "last_publish_ts": 1777534164,
  "items": [
    {
      "url": "https://www.e15.cz/byznys/doprava-a-logistika/skode-auto-prudce-vzrostl-zisk-automobilku-tahla-poptavka-po-elektromobilech-1432497",
      "title": "Benzín v ČR: 42,30 Kč/l – co to znamená pro řidiče",
      "summary": "Benzín v ČR se v posledním měsíci zdražil na 42,30 Kč/l, nafta na 45,10 Kč/l. Přesné výpočty, srovnání s předchozím rokem a praktické rady, kde najít nejlevnější čerpací stanice. Čtěte, jak to ovlivní váš rozpočet.",
      "filename": "benzinn-ceska-cena-42-30-kc-l.html",
      "published_at": "30. 04. 2026 09:27",
      "created": "2026-04-30 07:29:24",
      "score": 5.55,
      "source": "E15.cz",
      "is_archive": false,
      "category": "Ceny paliv",
      "entities": [
        "Benzina ORLEN",
        "MOL",
        "OPEC",
        "ČNB",
        "ČESMAD",
        "OMV",
        "Shell"
      ],
      "tags": [
        "benzín",
        "nafta",
        "ceny paliv",
        "tankování",
        "ČR"
      ]
    },
    {
      "url": "https://www.autorevue.cz/peugeot-v-cesku-zlevnuje-suv-5008-a-uvadi-edici-summer-blue-usetri-vam-slusny-balik",
      "title": "Benzín v ČR: Ceny, srovnání a tipy na nejlevnější tankování",
      "summary": "Litr benzínu v Praze letos stál 42,30 Kč, nafta 44,10 Kč. Přes 600 slov vám přinášíme detailní analýzu, srovnání s minulým rokem, tipy na nejlevnější stánky a předpověď budoucích cen. Připravte se na tankování bez překvapení!",
      "filename": "benzyn-v-cr-ceny-paliv.html",
      "published_at": "29. 04. 2026 17:01",
      "created": "2026-04-29 15:04:55",
      "score": 3.9,
      "source": "AutoRevue",
      "is_archive": false,
      "category": "Ceny paliv",
      "entities": [
        "Benzina ORLEN",
        "MOL",
        "OPEC",
        "ČNB",
        "MPO",
        "SÚKL"
      ],
      "tags": [
        "benzín",
        "nafta",
        "ceny paliv",
        "tankování",
        "ČR"
      ]
    },
    {
      "url": "https://www.novinky.cz/clanek/krimi-seniora-v-marianskych-laznich-mel-ohrozovat-nozem-policiste-ho-po-vypatrani-zase-pustili-hned-sel-vyloupit-benzinku-40575863",
      "title": "Benzín dnes 42,30 Kč – co to znamená pro české řidiče",
      "summary": "Průměrná cena benzínu v ČR se v posledním měsíci zvýšila o 3,5 %. Řidič, který tankuje 60 l, zaplatí o 204 Kč víc. V článku najdete srovnání, kde najít nejlevnější čerpací stanice a co přináší budoucí vývoj cen.",
      "filename": "benzinn-dnes-42-30-kc-co-to-znameni-pro-ceske-ridice.html",
      "published_at": "29. 04. 2026 17:01",
      "created": "2026-04-29 15:03:12",
      "score": 4.15,
      "source": "Novinky Ekonomika",
      "is_archive": false,
      "category": "Ceny paliv",
      "entities": [
        "Benzina ORLEN",
        "MOL",
        "OPEC",
        "ČNB",
        "MPO"
      ],
      "tags": [
        "benzín",
        "nafta",
        "ceny paliv",
        "tankování",
        "ČR"
      ]
    },
    {
      "url": "https://www.novinky.cz/clanek/ekonomika-cena-benzinu-v-usa-je-nejvyse-od-zacatku-valky-s-iranem-40575800",
      "title": "Cena benzínu v ČR: co se děje a proč",
      "summary": "Litr benzínu v Praze právě stojí 22,89 Kč, nejvyšší cena od začátku války s Íránem. Co to znamená pro řidiče v ČR, jak se to liší od minulého roku a kde najít nejlevnější čerpací stanice?",
      "filename": "cena-benzinu-v-cr-co-se-deluje.html",
      "published_at": "29. 04. 2026 09:23",
      "created": "2026-04-29 07:26:55",
      "score": 4.15,
      "source": "Novinky Ekonomika",
      "is_archive": false,
      "category": "Ceny paliv",
      "entities": [
        "Benzina ORLEN",
        "MOL",
        "OPEC",
        "ČNB",
        "ČESMAD",
        "MPO",
        "SÚKL"
      ],
      "tags": [
        "benzín",
        "nafta",
        "ceny paliv",
        "tankování",
        "ČR"
      ]
    },
    {
      "url": "https://www.e15.cz/investice/investicni-online-cena-benzinu-v-usa-je-nejvyse-od-zacatku-valky-s-iranem-1424330",
      "title": "Benzín v ČR: cena roste, co to znamená pro řidiče",
      "summary": "V Praze se cena benzínu posunula na 42,30 Kč/l, nafta 45,10 Kč/l. Přesné výpočty pro 55‑litrovou nádrž, srovnání s minulým rokem a tipy, kde natankovat nejlevněji. Připravte se na další výkyvy v cenách paliv.",
      "filename": "cena-benzinu-v-cr.html",
      "published_at": "29. 04. 2026 09:23",
      "created": "2026-04-29 07:25:17",
      "score": 4.25,
      "source": "E15.cz",
      "is_archive": false,
      "category": "Ceny paliv",
      "entities": [
        "Benzina ORLEN",
        "MOL",
        "OPEC",
        "ČNB",
        "ČESMAD",
        "MPO",
        "SÚKL"
      ],
      "tags": [
        "benzín",
        "nafta",
        "ceny paliv",
        "tankování",
        "ČR"
      ]
    },
    {
      "url": "https://www.auto.cz/zapomente-na-apple-nebo-sony-na-vlastni-auto-laka-sit-cerpacich-stanic-shell-160796",
      "title": "Benzín v ČR: 42,30 Kč/l – co to znamená pro řidiče",
      "summary": "Litr benzínu v Praze se dnes zvedl na 42,30 Kč, nafta na 45,10 Kč. Pro řidiče s 60‑litrovou nádrží to znamená přibližně 2 400 Kč navíc. V článku najdete, proč ceny stoupají, kolik zaplatíte a kde najít nejlevnější čerpací stanicu.",
      "filename": "benzin-v-cr-cena-42-30-kc-l.html",
      "published_at": "28. 04. 2026 17:15",
      "created": "2026-04-28 15:18:46",
      "score": 4.35,
      "source": "Auto.cz",
      "is_archive": false,
      "category": "Ceny paliv",
      "entities": [
        "Benzina ORLEN",
        "MOL",
        "OPEC",
        "ČNB",
        "ČESMAD",
        "MPO",
        "SÚKL",
        "Shell",
        "OMV"
      ],
      "tags": [
        "benzín",
        "nafta",
        "ceny paliv",
        "tankování",
        "ČR"
      ]
    },
    {
      "url": "https://www.e15.cz/investice/investicni-online-ropa-kvuli-konfliktu-na-blizkem-vychode-dal-zdrazuje-1424330",
      "title": "Benzín a nafta: Ceny v ČR se zvyšují",
      "summary": "Ceny benzínu a nafty v ČR se v posledních týdnech zvýšily. Litr Natural 95 stojí nyní 42,30 Kč, nafta 44,10 Kč. Přinášíme analýzu příčin, dopad na řidiče a tipy, kde najít nejlevnější čerpací stanice.",
      "filename": "benzin-nafta-ceny-ceska.html",
      "published_at": "28. 04. 2026 17:15",
      "created": "2026-04-28 15:17:02",
      "score": 6.55,
      "source": "E15.cz",
      "is_archive": false,
      "category": "Ceny paliv",
      "entities": [
        "Benzina ORLEN",
        "MOL",
        "OPEC",
        "ČNB",
        "ČESMAD",
        "MPO",
        "SÚKL"
      ],
      "tags": [
        "benzín",
        "nafta",
        "ceny paliv",
        "tankování",
        "ČR"
      ]
    },
    {
      "url": "https://zpravy.aktualne.cz/ekonomika/auto/technika-a-design/evropa-resi-penalty-cina-vyrabi-auta-sefdesigner-jozef-kaban-popisuje-stret-dvou-svetu/r~aaa294deb0b5e38bedff2efbd127fb0a/",
      "title": "Benzín v ČR: 42,30 Kč/l – co to znamená pro řidiče",
      "summary": "V ČR se cena benzínu zvedla na 42,30 Kč/l, nafta na 43,10 Kč/l. Přesvědčte se, kolik zaplatíte na 55 l, jaký dopad má to na peněženku řidiče a kde najít nejlevnější čerpací stanice v Praze, Brně a Ostravě.",
      "filename": "benzinn-ceska-cena-42-30-kc-l.html",
      "published_at": "28. 04. 2026 09:30",
      "created": "2026-04-28 07:37:43",
      "score": 3.6,
      "source": "Aktuálně Ekonomika",
      "is_archive": false,
      "category": "Ceny paliv",
      "entities": [
        "Benzina ORLEN",
        "MOL",
        "OPEC",
        "ČNB",
        "ČESMAD",
        "MPO",
        "SÚKL",
        "Shell",
        "OMV"
      ],
      "tags": [
        "benzín",
        "nafta",
        "ceny paliv",
        "tankování",
        "ČR"
      ]
    },
    {
      "url": "https://www.novinky.cz/clanek/auto-stellantis-se-v-krizi-zacne-soustredit-na-ctyri-klicove-znacky-dalsich-deset-automobilek-se-prizpusobi-40575551",
      "title": "Benzín v ČR: ceny, tankování a co čekat v roce 2026",
      "summary": "Litr benzínu v Praze stojí 38,90 Kč, nafta 42,30 Kč. Přesné výpočty, proč se ceny zvedají a kde najít nejlevnější stánky v ČR. Připravte se na budoucí změny cen paliv.",
      "filename": "benzin-ceny-paliv-2026.html",
      "published_at": "28. 04. 2026 09:30",
      "created": "2026-04-28 07:35:01",
      "score": 3.95,
      "source": "Novinky Ekonomika",
      "is_archive": false,
      "category": "Ceny paliv",
      "entities": [
        "Benzina ORLEN",
        "MOL",
        "OPEC",
        "ČNB",
        "ČESMAD",
        "MPO",
        "SÚKL"
      ],
      "tags": [
        "benzín",
        "nafta",
        "ceny paliv",
        "tankování",
        "ČR"
      ]
    },
    {
      "url": "https://www.e15.cz/byznys/prumysl-a-energetika/regulace-cen-benzinu-a-nafty-bude-pokracovat-i-v-kvetnu-oznamila-schillerova-1432421",
      "title": "Benzín a nafta: 400 Kč úspora na plné nádrži v květnu",
      "summary": "V květnu se na české čerpací sítě vrací regulace marží a snížení spotřební daně na naftu. Díky tomu řidič s 60 l nádrží ušetří až 400 Kč. Přinášíme aktuální ceny, výpočty a tipy, kde natankovat nejlevněji.",
      "filename": "benzina-nafta-400-kc-uspora-kvetn.html",
      "published_at": "28. 04. 2026 09:30",
      "created": "2026-04-28 07:33:01",
      "score": 4.25,
      "source": "E15.cz",
      "is_archive": false,
      "category": "Ceny paliv",
      "entities": [
        "Benzina ORLEN",
        "MOL",
        "OPEC",
        "ČNB",
        "ČESMAD",
        "MPO",
        "SÚKL"
      ],
      "tags": [
        "benzín",
        "nafta",
        "ceny paliv",
        "tankování",
        "ČR"
      ]
    },
    {
      "url": "https://ct24.ceskatelevize.cz/clanek/svet/hodnota-majetku-ruskych-miliardaru-i-pres-sankce-rekordne-vzrostla-pise-forbes-372710",
      "title": "Benzín a nafta v ČR: ceny, tankování a výhled na 2026",
      "summary": "Ceny benzínu a nafty v ČR se v posledních týdnech zvedly o více než 10 %. Přesněji: Natural 95 nyní 42,30 Kč/l, nafta 46,10 Kč/l. V článku najdete výpočet nákladů na tankování, tipy na levné stánky a analýzu, jak globální sankce ovlivňují české řidiče.",
      "filename": "benzyn-nafta-ceny-2026.html",
      "published_at": "27. 04. 2026 16:55",
      "created": "2026-04-27 15:00:37",
      "score": 3.7,
      "source": "ČT24 Ekonomika",
      "is_archive": false,
      "category": "Ceny paliv",
      "entities": [
        "Benzina ORLEN",
        "MOL",
        "OPEC",
        "ČNB",
        "ČESMAD",
        "MPO",
        "SÚKL"
      ],
      "tags": [
        "benzín",
        "nafta",
        "ceny paliv",
        "tankování",
        "ČR"
      ]
    },
    {
      "url": "https://www.novinky.cz/clanek/auto-foto-automobilove-klenoty-se-ukazaly-na-golfovem-hristi-v-praze-40575361",
      "title": "Benzín a nafta v ČR: 42,30 Kč/l – co to znamená pro řidiče",
      "summary": "Litr nafty se v Praze zvýšil na 42,30 Kč, benzín na 43,10 Kč. Přesné výpočty, srovnání s minulým rokem a praktické rady, kde najít nejlevnější čerpací stanice. Připravte se na další náklady na tankování.",
      "filename": "benzina-nafta-cena-ceska-2026.html",
      "published_at": "27. 04. 2026 16:55",
      "created": "2026-04-27 14:58:58",
      "score": 3.95,
      "source": "Novinky Ekonomika",
      "is_archive": false,
      "category": "Ceny paliv",
      "entities": [
        "Benzina ORLEN",
        "MOL",
        "OPEC",
        "ČNB",
        "ČESMAD",
        "MPO",
        "SÚKL"
      ],
      "tags": [
        "benzín",
        "nafta",
        "ceny paliv",
        "tankování",
        "ČR"
      ]
    },
    {
      "url": "https://www.e15.cz/investice/investicni-online-regulace-cen-benzinu-a-nafty-bude-pokracovat-chybi-ale-podpis-zakona-1424330",
      "title": "Benzín a nafta v ČR: ceny se zvyšují, co to znamená pro řid…",
      "summary": "Ceny benzínu a nafty v ČR se v posledních týdnech zvedly. Litr Natural 95 stojí nyní 42,30 Kč, nafta 44,10 Kč. To znamená, že řidič s 60 l nádrží zaplatí o 204 Kč víc než před rokem. V článku najdete příčiny, výpočet nákladů a tipy, kde natankovat nejlevněji.",
      "filename": "benzyn-nafta-ceny-cesko.html",
      "published_at": "27. 04. 2026 16:55",
      "created": "2026-04-27 14:57:23",
      "score": 4.25,
      "source": "E15.cz",
      "is_archive": false,
      "category": "Ceny paliv",
      "entities": [
        "Benzina ORLEN",
        "MOL",
        "OPEC",
        "ČNB",
        "ČESMAD",
        "MPO",
        "SÚKL"
      ],
      "tags": [
        "benzín",
        "nafta",
        "ceny paliv",
        "tankování",
        "ČR"
      ]
    },
    {
      "url": "https://zpravy.aktualne.cz/ekonomika/jarni-potravinove-sbirky-se-zucastnil-rekordni-pocet-obchodu-vybralo-se-o-sto-tun-vic-nez-loni/r~aaa295e124d0f7e5673074d9bae58881/",
      "title": "Benzín v ČR: ceny, tankování a tipy na nejlevnější čerpací…",
      "summary": "Litr benzínu v Praze dnes stojí 42,30 Kč, nafta 43,10 Kč. Přes 600 slov vám přinášíme detailní pohled na faktory, které ovlivňují ceny, výpočet nákladů na tankování a tipy, kde najít nejlevnější čerpací stanice v ČR.",
      "filename": "benzinn-ceska-cena-levnejsi-ctepaci-stanice.html",
      "published_at": "27. 04. 2026 10:40",
      "created": "2026-04-27 08:45:57",
      "score": 3.6,
      "source": "Aktuálně Ekonomika",
      "is_archive": false,
      "category": "Ceny paliv",
      "entities": [
        "Benzina ORLEN",
        "MOL",
        "OPEC",
        "ČNB",
        "ČESMAD",
        "MPO",
        "SÚKL"
      ],
      "tags": [
        "benzín",
        "nafta",
        "ceny paliv",
        "tankování",
        "ČR"
      ]
    },
    {
      "url": "https://www.e15.cz/byznys/technologie-a-media/propast-se-prohlubuje-ai-rusi-tisice-mist-v-it-nova-vznikaji-jen-pro-vyvolene-1432395",
      "title": "Benzín a nafta: Ceny se zvedají, co to znamená pro řidiče",
      "summary": "Před rokem litr nafty stál 38,90 Kč, dnes 42,30 Kč – řidič s 60 l nádrží zaplatí o 204 Kč víc. V článku najdete konkrétní příklady, kde natankovat nejlevněji a jak se vyrovnat s rostoucími cenami.",
      "filename": "benzina-nafta-ceny-rozvoj.html",
      "published_at": "27. 04. 2026 10:39",
      "created": "2026-04-27 08:44:09",
      "score": 3.75,
      "source": "E15.cz",
      "is_archive": false,
      "category": "Ceny paliv",
      "entities": [
        "Benzina ORLEN",
        "MOL",
        "OPEC",
        "ČNB",
        "ČESMAD",
        "MPO",
        "SÚKL"
      ],
      "tags": [
        "benzín",
        "nafta",
        "ceny paliv",
        "tankování",
        "ČR"
      ]
    },
    {
      "url": "https://ct24.ceskatelevize.cz/clanek/domaci/maximalni-ceny-paliv-o-vikendu-opet-o-vyssi-desitky-haleru-vzrostou-372764",
      "title": "Benzín a nafta: ceny vzrostou o desítky haléřů o víkendu",
      "summary": "V pátek se maximální cena benzínu zvýšila na 42,19 Kč/l a nafty na 42,86 Kč/l. O víkendu se tyto ceny opět zvýší o desítky haléřů. Připravte se na další náklady – řidiči z Prahy, Brna a Ostravy se mohou těšit na vyšší účty. Článek vysvětluje, proč se ceny mění a kde najít nejlev…",
      "filename": "benzyn-nafta-ceny-vikend.html",
      "published_at": "27. 04. 2026 10:40",
      "created": "2026-04-27 08:42:17",
      "score": 4.0,
      "source": "ČT24 Ekonomika",
      "is_archive": false,
      "category": "Ceny paliv",
      "entities": [
        "Benzina ORLEN",
        "MOL",
        "OPEC",
        "ČNB",
        "ČESMAD",
        "MPO",
        "SÚKL",
        "Shell",
        "OMV"
      ],
      "tags": [
        "benzín",
        "nafta",
        "ceny paliv",
        "tankování",
        "ČR"
      ]
    }
  ]
}